AUTHORS
LICENSE
MANIFEST.in
README.rst
setup.py
django_testimony.egg-info/PKG-INFO
django_testimony.egg-info/SOURCES.txt
django_testimony.egg-info/dependency_links.txt
django_testimony.egg-info/not-zip-safe
django_testimony.egg-info/requires.txt
django_testimony.egg-info/top_level.txt
testimony/__init__.py
testimony/__init__.pyc
testimony/admin.py
testimony/admin.pyc
testimony/cms_plugins.py
testimony/cms_plugins.pyc
testimony/forms.py
testimony/models.py
testimony/models.pyc
testimony/settings.py
testimony/settings.pyc
testimony/urls.py
testimony/views.py
testimony/migrations/0001_initial.py
testimony/migrations/0001_initial.pyc
testimony/migrations/0002_auto__add_testimonialproduct__add_field_testimonialplugin_product__del.py
testimony/migrations/0002_auto__add_testimonialproduct__add_field_testimonialplugin_product__del.pyc
testimony/migrations/__init__.py
testimony/migrations/__init__.pyc
testimony/static/jquery-simplyscroll/README.md
testimony/static/jquery-simplyscroll/buttons.png
testimony/static/jquery-simplyscroll/jquery.simplyscroll.css
testimony/static/jquery-simplyscroll/jquery.simplyscroll.js
testimony/static/jquery-simplyscroll/jquery.simplyscroll.min.js
testimony/static/vticker/vticker.js
testimony/templates/testimony/list_default.html
testimony/templates/testimony/list_page.html
testimony/templates/testimony/plugin.html
testimony/templates/testimony/rotator.html
testimony/templates/testimony/vticker.html