Metadata-Version: 1.1
Name: django-testimony
Version: 0.0.2b1
Summary: A Django app that will create a pluggable django-cms testimony form and content plugin within your project..
Home-page: https://bitbucket.org/oddotterco/django-testimony
Author: Odd Otter Co
Author-email: testimony@oddotter.com
License: BSD
Keywords: django,cms,theme
Platform: Linux
Classifier: Development Status :: 4 - Beta
Classifier: Framework :: Django
Classifier: Intended Audience :: Developers
Classifier: License :: OSI Approved :: BSD License
Classifier: Operating System :: OS Independent
Classifier: Programming Language :: Python
Classifier: Topic :: Internet :: WWW/HTTP
Classifier: Topic :: Internet :: WWW/HTTP :: Dynamic Content
